cfapi/__init__.py
cfapi/base.py
cfapi/contest.py
cfapi/exceptions.py
cfapi/funcs.py
cfapi/problem.py
cfapi/profile.py
cfapi-1.0.0.dist-info/METADATA
cfapi-1.0.0.dist-info/WHEEL
cfapi-1.0.0.dist-info/top_level.txt
cfapi-1.0.0.dist-info/RECORD
