Metadata-Version: 2.1
Name: cfapi
Version: 1.0.0
Summary: An unofficial Codeforces API, that gives you access to contests, problems, and profiles on Codeforces.com
Home-page: https://github.com/RealA10N/cfapi
Author: RealA10N
Author-email: downtown2u@gmail.com
License: MIT
Keywords: Codeforces Codeforces.com Competitive Programming API Wrapper Scraper
Platform: UNKNOWN
Requires-Python: >=3.6
Requires-Dist: requests (<3,>=2.26)
Requires-Dist: beautifulsoup4 (<5,>=4.10)
Requires-Dist: lxml (<5,>=4.6)
